MANIFEST.in
setup.py
errors/404.html
errors/500.html
pywebserver/HTTPServer.py
pywebserver/__init__.py
pywebserver.egg-info/PKG-INFO
pywebserver.egg-info/SOURCES.txt
pywebserver.egg-info/dependency_links.txt
pywebserver.egg-info/not-zip-safe
pywebserver.egg-info/top_level.txt