Metadata-Version: 1.0
Name: pywebserver
Version: 0.1
Summary: An HTTP server written from scratch
Home-page: http://github.com/Squaar/webserver
Author: Matt Dumford
Author-email: mdumford99@gmail.com
License: MIT
Platform: UNKNOWN
